fastapi_sso/__init__.py
fastapi_sso/pkce.py
fastapi_sso/py.typed
fastapi_sso/sso/__init__.py
fastapi_sso/sso/base.py
fastapi_sso/sso/facebook.py
fastapi_sso/sso/fitbit.py
fastapi_sso/sso/generic.py
fastapi_sso/sso/github.py
fastapi_sso/sso/gitlab.py
fastapi_sso/sso/google.py
fastapi_sso/sso/kakao.py
fastapi_sso/sso/line.py
fastapi_sso/sso/linkedin.py
fastapi_sso/sso/microsoft.py
fastapi_sso/sso/naver.py
fastapi_sso/sso/notion.py
fastapi_sso/sso/spotify.py
fastapi_sso/sso/twitter.py
fastapi_sso/sso/yandex.py
fastapi_sso/state.py
fastapi_sso-0.15.0.dist-info/LICENSE.md
fastapi_sso-0.15.0.dist-info/METADATA
fastapi_sso-0.15.0.dist-info/WHEEL
fastapi_sso-0.15.0.dist-info/RECORD
