Metadata-Version: 2.1
Name: fastapi-sso
Version: 0.15.0
Summary: FastAPI plugin to enable SSO to most common providers (such as Facebook login, Google login and login via Microsoft Office 365 Account)
Home-page: https://tomasvotava.github.io/fastapi-sso/
License: MIT
Keywords: fastapi,sso,oauth,google,facebook,spotify,linkedin
Author: Tomas Votava
Author-email: info@tomasvotava.eu
Requires-Python: >=3.8,<4.0
Classifier: License :: OSI Approved :: MIT License
Classifier: Programming Language :: Python :: 3
Classifier: Programming Language :: Python :: 3.8
Classifier: Programming Language :: Python :: 3.9
Classifier: Programming Language :: Python :: 3.10
Classifier: Programming Language :: Python :: 3.11
Classifier: Programming Language :: Python :: 3.12
Requires-Dist: fastapi (>=0.80)
Requires-Dist: httpx (>=0.23.0)
Requires-Dist: oauthlib (>=3.1.0)
Requires-Dist: pydantic[email] (>=1.8.0)
Project-URL: Documentation, https://tomasvotava.github.io/fastapi-sso/
Project-URL: Repository, https://github.com/tomasvotava/fastapi-sso
